redengine/__init__.py
redengine/_base.py
redengine/_setup.py
redengine/_version.py
redengine/application.py
redengine/exc.py
redengine/session.py
redengine/args/__init__.py
redengine/args/builtin.py
redengine/args/secret.py
redengine/conditions/__init__.py
redengine/conditions/func.py
redengine/conditions/meta.py
redengine/conditions/parameter.py
redengine/conditions/scheduler.py
redengine/conditions/time.py
redengine/conditions/task/__init__.py
redengine/conditions/task/task.py
redengine/conditions/task/utils.py
redengine/core/__init__.py
redengine/core/hook.py
redengine/core/meta.py
redengine/core/schedule.py
redengine/core/task.py
redengine/core/condition/__init__.py
redengine/core/condition/base.py
redengine/core/condition/statement.py
redengine/core/condition/utils.py
redengine/core/log/__init__.py
redengine/core/log/adapter.py
redengine/core/parameters/__init__.py
redengine/core/parameters/arguments.py
redengine/core/parameters/parameters.py
redengine/core/time/__init__.py
redengine/core/time/anchor.py
redengine/core/time/base.py
redengine/core/time/utils.py
redengine/core/utils/__init__.py
redengine/core/utils/meta.py
redengine/core/utils/pickle.py
redengine/core/utils/process.py
redengine/log/__init__.py
redengine/log/defaults.py
redengine/log/handlers.py
redengine/log/log_record.py
redengine/parameters/__init__.py
redengine/parameters/func.py
redengine/parse/__init__.py
redengine/parse/condition.py
redengine/parse/time.py
redengine/parse/_condition/__init__.py
redengine/parse/_condition/condition_item.py
redengine/parse/_condition/string.py
redengine/parse/_time/__init__.py
redengine/parse/_time/string.py
redengine/parse/_time/time_item.py
redengine/parse/utils/__init__.py
redengine/parse/utils/cond.py
redengine/parse/utils/exception.py
redengine/parse/utils/parser.py
redengine/parse/utils/string_parser.py
redengine/parse/utils/utils.py
redengine/pybox/__init__.py
redengine/pybox/container/__init__.py
redengine/pybox/container/visitor.py
redengine-2.0.1.dist-info/LICENSE
redengine-2.0.1.dist-info/METADATA
redengine-2.0.1.dist-info/WHEEL
redengine-2.0.1.dist-info/top_level.txt
redengine-2.0.1.dist-info/RECORD
